{
  "e1_lattice": {
    "passed": 15,
    "failed": 0,
    "tests": [
      {
        "name": "x>0 <: x>=0",
        "status": "PASS"
      },
      {
        "name": "x>5 <: x>0",
        "status": "PASS"
      },
      {
        "name": "\u00ac(x>=0 <: x>0)",
        "status": "PASS"
      },
      {
        "name": "\u22a5 <: anything",
        "status": "PASS"
      },
      {
        "name": "anything <: \u22a4",
        "status": "PASS"
      },
      {
        "name": "\u00ac(\u22a4 <: x>0)",
        "status": "PASS"
      },
      {
        "name": "join(x>0, x<0) is satisfiable",
        "status": "PASS"
      },
      {
        "name": "x>0 <: join(x>0, x<0)",
        "status": "PASS"
      },
      {
        "name": "meet(x>=0, x<=10) is satisfiable",
        "status": "PASS"
      },
      {
        "name": "meet(x>=0, x<=10) <: x>=0",
        "status": "PASS"
      },
      {
        "name": "widen produces a type",
        "status": "PASS"
      },
      {
        "name": "narrow produces a type",
        "status": "PASS"
      },
      {
        "name": "\u03b1-renamed types equivalent",
        "status": "PASS"
      },
      {
        "name": "and predicate pretty",
        "status": "PASS"
      },
      {
        "name": "or predicate pretty",
        "status": "PASS"
      }
    ]
  },
  "e2_cegar": {
    "programs": [
      {
        "name": "div_by_zero_guarded",
        "description": "Division guarded by y != 0",
        "expected_bugs": 0,
        "actual_alarms": 0,
        "verified_bugs": 0,
        "spurious": 0,
        "converged": true,
        "iterations": 1,
        "predicates": 8,
        "time_ms": 9.244457993190736,
        "correct": true
      },
      {
        "name": "div_by_zero_unguarded",
        "description": "Unguarded division",
        "expected_bugs": 1,
        "actual_alarms": 1,
        "verified_bugs": 1,
        "spurious": 0,
        "converged": true,
        "iterations": 1,
        "predicates": 7,
        "time_ms": 25.27808299055323,
        "correct": true
      },
      {
        "name": "none_deref_guarded",
        "description": "None check before attribute access",
        "expected_bugs": 0,
        "actual_alarms": 0,
        "verified_bugs": 0,
        "spurious": 0,
        "converged": true,
        "iterations": 1,
        "predicates": 8,
        "time_ms": 11.350874992785975,
        "correct": true
      },
      {
        "name": "none_deref_unguarded",
        "description": "No None check before attribute access",
        "expected_bugs": 1,
        "actual_alarms": 1,
        "verified_bugs": 1,
        "spurious": 0,
        "converged": true,
        "iterations": 1,
        "predicates": 7,
        "time_ms": 15.008999995188788,
        "correct": true
      },
      {
        "name": "isinstance_narrowing",
        "description": "isinstance-based type narrowing",
        "expected_bugs": 0,
        "actual_alarms": 0,
        "verified_bugs": 0,
        "spurious": 0,
        "converged": true,
        "iterations": 1,
        "predicates": 9,
        "time_ms": 0.444875011453405,
        "correct": true
      },
      {
        "name": "loop_div_zero",
        "description": "Division after loop with guard",
        "expected_bugs": 0,
        "actual_alarms": 0,
        "verified_bugs": 0,
        "spurious": 0,
        "converged": true,
        "iterations": 1,
        "predicates": 8,
        "time_ms": 4.86908400489483,
        "correct": true
      },
      {
        "name": "chained_none_check",
        "description": "Chained None checks",
        "expected_bugs": 0,
        "actual_alarms": 0,
        "verified_bugs": 0,
        "spurious": 0,
        "converged": true,
        "iterations": 1,
        "predicates": 9,
        "time_ms": 1.535832998342812,
        "correct": true
      },
      {
        "name": "arithmetic_overflow",
        "description": "Recursive factorial",
        "expected_bugs": 0,
        "actual_alarms": 0,
        "verified_bugs": 0,
        "spurious": 0,
        "converged": true,
        "iterations": 1,
        "predicates": 8,
        "time_ms": 0.28987500991206616,
        "correct": true
      },
      {
        "name": "list_index_guarded",
        "description": "List index with length check",
        "expected_bugs": 0,
        "actual_alarms": 0,
        "verified_bugs": 0,
        "spurious": 0,
        "converged": true,
        "iterations": 1,
        "predicates": 8,
        "time_ms": 0.2228330122306943,
        "correct": true
      },
      {
        "name": "complex_guards",
        "description": "Multiple interacting guards",
        "expected_bugs": 0,
        "actual_alarms": 0,
        "verified_bugs": 0,
        "spurious": 0,
        "converged": true,
        "iterations": 1,
        "predicates": 13,
        "time_ms": 0.8556250104447827,
        "correct": true
      },
      {
        "name": "interprocedural_bug",
        "description": "Bug requires interprocedural analysis",
        "expected_bugs": 1,
        "actual_alarms": 1,
        "verified_bugs": 1,
        "spurious": 0,
        "converged": true,
        "iterations": 1,
        "predicates": 8,
        "time_ms": 12.282750001759268,
        "correct": true
      },
      {
        "name": "mutual_recursion",
        "description": "Mutually recursive functions",
        "expected_bugs": 0,
        "actual_alarms": 0,
        "verified_bugs": 0,
        "spurious": 0,
        "converged": true,
        "iterations": 1,
        "predicates": 9,
        "time_ms": 0.8470830071019009,
        "correct": true
      }
    ],
    "total_correct": 12,
    "total": 12,
    "accuracy": 1.0
  },
  "e3_interprocedural": {
    "programs": [
      {
        "name": "call_chain",
        "functions_analyzed": 2,
        "summaries": 2,
        "expected_summaries": 2,
        "alarms": 1,
        "sccs": 2,
        "time_ms": 1.9382089958526194
      },
      {
        "name": "recursive",
        "functions_analyzed": 2,
        "summaries": 2,
        "expected_summaries": 2,
        "alarms": 0,
        "sccs": 2,
        "time_ms": 8.65516699559521
      },
      {
        "name": "multi_callers",
        "functions_analyzed": 3,
        "summaries": 3,
        "expected_summaries": 3,
        "alarms": 2,
        "sccs": 3,
        "time_ms": 5.250916990917176
      }
    ],
    "summaries_computed": 7
  },
  "e4_guard_harvesting": {
    "programs": [
      {
        "name": "div_by_zero_guarded",
        "guards_found": 1,
        "guard_types": [
          "NEQ"
        ]
      },
      {
        "name": "div_by_zero_unguarded",
        "guards_found": 0,
        "guard_types": []
      },
      {
        "name": "none_deref_guarded",
        "guards_found": 1,
        "guard_types": [
          "IS_NOT_NONE"
        ]
      },
      {
        "name": "none_deref_unguarded",
        "guards_found": 0,
        "guard_types": []
      },
      {
        "name": "isinstance_narrowing",
        "guards_found": 2,
        "guard_types": [
          "ISINSTANCE",
          "ISINSTANCE"
        ]
      },
      {
        "name": "loop_div_zero",
        "guards_found": 1,
        "guard_types": [
          "GT"
        ]
      },
      {
        "name": "chained_none_check",
        "guards_found": 2,
        "guard_types": [
          "IS_NONE",
          "IS_NONE"
        ]
      },
      {
        "name": "arithmetic_overflow",
        "guards_found": 1,
        "guard_types": [
          "LE"
        ]
      },
      {
        "name": "list_index_guarded",
        "guards_found": 1,
        "guard_types": [
          "LEN_GT"
        ]
      },
      {
        "name": "complex_guards",
        "guards_found": 6,
        "guard_types": [
          "IS_NONE",
          "LEN_EQ",
          "IS_NOT_NONE",
          "NEQ",
          "ISINSTANCE",
          "GT"
        ]
      },
      {
        "name": "interprocedural_bug",
        "guards_found": 1,
        "guard_types": [
          "GT"
        ]
      },
      {
        "name": "mutual_recursion",
        "guards_found": 2,
        "guard_types": [
          "EQ",
          "EQ"
        ]
      }
    ],
    "total_guards": 18
  },
  "e5_widening": {
    "tests": [
      {
        "name": "join sequence grows",
        "status": "PASS"
      },
      {
        "name": "widening stabilizes",
        "status": "PASS"
      },
      {
        "name": "widened type retains x>=0",
        "status": "PASS"
      },
      {
        "name": "narrowing recovers precision",
        "status": "PASS"
      },
      {
        "name": "domain widening preserves common predicates",
        "status": "PASS"
      }
    ],
    "passed": 5,
    "failed": 0
  },
  "e6_end_to_end": {
    "programs": [
      {
        "name": "config_parser",
        "functions": 2,
        "loc": 25,
        "cegar_alarms": 0,
        "cegar_verified": 0,
        "cegar_iterations": 1,
        "cegar_converged": true,
        "interproc_alarms": 0,
        "interproc_summaries": 0,
        "time_ms": 32.25045799626969
      },
      {
        "name": "retry_logic",
        "functions": 1,
        "loc": 13,
        "cegar_alarms": 0,
        "cegar_verified": 0,
        "cegar_iterations": 1,
        "cegar_converged": true,
        "interproc_alarms": 0,
        "interproc_summaries": 0,
        "time_ms": 2.736458001891151
      },
      {
        "name": "tree_operations",
        "functions": 2,
        "loc": 19,
        "cegar_alarms": 0,
        "cegar_verified": 0,
        "cegar_iterations": 1,
        "cegar_converged": true,
        "interproc_alarms": 2,
        "interproc_summaries": 2,
        "time_ms": 33.904249998158775
      }
    ]
  },
  "e7_performance": {
    "sizes": [
      {
        "n_functions": 2,
        "loc": 14,
        "time_ms": 23.451000000932254,
        "alarms": 0,
        "predicates": 9,
        "ms_per_function": 11.725500000466127
      },
      {
        "n_functions": 5,
        "loc": 35,
        "time_ms": 33.169500005897135,
        "alarms": 0,
        "predicates": 12,
        "ms_per_function": 6.633900001179427
      },
      {
        "n_functions": 10,
        "loc": 70,
        "time_ms": 61.260167000000365,
        "alarms": 0,
        "predicates": 17,
        "ms_per_function": 6.1260167000000365
      },
      {
        "n_functions": 20,
        "loc": 140,
        "time_ms": 124.43574999633711,
        "alarms": 0,
        "predicates": 27,
        "ms_per_function": 6.221787499816855
      },
      {
        "n_functions": 50,
        "loc": 350,
        "time_ms": 149.43941700039431,
        "alarms": 0,
        "predicates": 57,
        "ms_per_function": 2.9887883400078863
      }
    ]
  }
}