{
  "experiment": "state_abstraction_soundness",
  "n_concrete_states": 5,
  "n_actions": 3,
  "state_dim": 2,
  "seed": 42,
  "grid_results": [
    {
      "grid_size": 2,
      "n_abstract_states": 4,
      "concrete_safety_prob": 0.568165,
      "abstract_safety_prob": 0.592515,
      "overapproximation_gap": 0.02435,
      "elapsed_s": 0.0003
    },
    {
      "grid_size": 4,
      "n_abstract_states": 16,
      "concrete_safety_prob": 0.568165,
      "abstract_safety_prob": 0.568165,
      "overapproximation_gap": 0.0,
      "elapsed_s": 0.0004
    },
    {
      "grid_size": 8,
      "n_abstract_states": 64,
      "concrete_safety_prob": 0.568165,
      "abstract_safety_prob": 0.568165,
      "overapproximation_gap": 0.0,
      "elapsed_s": 0.0011
    },
    {
      "grid_size": 16,
      "n_abstract_states": 256,
      "concrete_safety_prob": 0.568165,
      "abstract_safety_prob": 0.568165,
      "overapproximation_gap": 0.0,
      "elapsed_s": 0.0039
    },
    {
      "grid_size": 32,
      "n_abstract_states": 1024,
      "concrete_safety_prob": 0.568165,
      "abstract_safety_prob": 0.568165,
      "overapproximation_gap": 0.0,
      "elapsed_s": 0.0186
    }
  ],
  "monotone_refinement": true
}